PantzAI/VQE_2q_FakeManila.py
PantzAI/__init__.py
PantzAI-1.dist-info/LICENSE
PantzAI-1.dist-info/METADATA
PantzAI-1.dist-info/WHEEL
PantzAI-1.dist-info/top_level.txt
PantzAI-1.dist-info/RECORD
