Metadata-Version: 2.1
Name: PantzAI
Version: 1
Summary: Implementation of RL techniques for defining pulse-based ansatz in VQE processes.
Author-email: Riccardo Marega <maregariccardo.rm0@gmail.com>
Project-URL: homepage, https://github.com/RiCkymare00/PantzAI
Classifier: Programming Language :: Python :: 3
Classifier: Operating System :: OS Independent
Requires-Python: >=3.6
License-File: LICENSE
